strainer/__init__.py
strainer/context.py
strainer/exceptions.py
strainer/fields.py
strainer/formatters.py
strainer/structure.py
strainer/validators.py
strainer_2020-1.4.0.dist-info/LICENSE
strainer_2020-1.4.0.dist-info/METADATA
strainer_2020-1.4.0.dist-info/WHEEL
strainer_2020-1.4.0.dist-info/top_level.txt
strainer_2020-1.4.0.dist-info/RECORD
