Metadata-Version: 2.1
Name: strainer-2020
Version: 1.4.0
Summary: Fast functional serializers
Home-page: http://github.com/zgoda/strainer
Author: Alex Kessinger
Author-email: voidfiles@gmail.com
Maintainer: Jarek Zgoda
Maintainer-email: jarek.zgoda@gmail.com
License: Apache 2.0
Platform: UNKNOWN
Classifier: Intended Audience :: Developers
Classifier: Natural Language :: English
Classifier: License :: OSI Approved :: Apache Software License
Classifier: Programming Language :: Python
Classifier: Programming Language :: Python :: 3
Classifier: Programming Language :: Python :: 3 :: Only
Classifier: Programming Language :: Python :: 3.6
Classifier: Programming Language :: Python :: 3.7
Classifier: Programming Language :: Python :: 3.8
Classifier: Programming Language :: Python :: 3.9
Classifier: Programming Language :: Python :: Implementation :: CPython
Classifier: Programming Language :: Python :: Implementation :: PyPy
Classifier: Topic :: Software Development :: Libraries :: Python Modules
Classifier: Development Status :: 5 - Production/Stable
Requires-Python: ~=3.6
Requires-Dist: aniso8601
